vaxmethod/__init__.py
vaxmethod/temp.py
vaxmethod-0.0.1.dist-info/LICENSE.txt
vaxmethod-0.0.1.dist-info/METADATA
vaxmethod-0.0.1.dist-info/WHEEL
vaxmethod-0.0.1.dist-info/top_level.txt
vaxmethod-0.0.1.dist-info/RECORD
